bitcron
