Metadata-Version: 1.0
Name: bitcron
Version: 0.0.9
Summary: Command Line Interface for Bitcron
Home-page: https://bitcron.com
Author: Hepochen
Author-email: hepochen@gmail.com
License: UNKNOWN
Platform: any
